[
  {
    "gameid": "nba.g.2021120218",
    "global_gameid": "nba.g.2374546",
    "start_time": "Fri, 03 Dec 2021 00:30:00 +0000",
    "is_time_tba": false,
    "season_phase_id": "season.phase.season",
    "game_type": "Regular Season",
    "winning_team_id": null,
    "is_rank_upset": null,
    "is_spread_upset": null,
    "outcome_type": null,
    "home_team_id": "nba.t.18",
    "away_team_id": "nba.t.4",
    "navigation_links": {
      "tickets": {
        "url": "https://seatgeek.com/new-york-knicks-tickets/?aid=14&date=2021-12-02"
      },
      "boxscore": {
        "url": "/nba/chicago-bulls-new-york-knicks-2021120218/"
      },
      "match_page": {
        "url": "/nba/chicago-bulls-new-york-knicks-2021120218/"
      },
      "league_home": {
        "url": "/nba/"
      },
      "league_scores": {
        "url": "/nba/scoreboard/"
      }
    },
    "sportacular_url": "ysportacular://v2/scores/details?gameId=nba.g.2021120218&sport=nba",
    "status_display_name": "7:30 pm ET",
    "status_description": "Pregame",
    "status_type": "status.type.pregame",
    "total_away_points": null,
    "current_period_id": null,
    "total_home_points": null,
    "total_away_shootout_points": null,
    "total_home_shootout_points": null,
    "home_team_stats": null,
    "away_team_stats": null,
    "game_period_balls": null,
    "game_period_strikes": null,
    "game_period_outs": null,
    "yards_to_endzone": null,
    "start_yardline": null,
    "distance": null,
    "down": null,
    "team_in_possession": null,
    "power_play_strength_home": null,
    "power_play_strength_away": null,
    "game_time_elapsed": null,
    "game_time_elapsed_display": null,
    "inning_status": null,
    "away_timeouts": null,
    "home_timeouts": null,
    "is_halftime": null,
    "minimum_periods": null,
    "game_periods": [],
    "baserunners": null,
    "season": "2021",
    "subleague": null,
    "subleague_display_name": null,
    "agg_score": null,
    "leg_number": null,
    "tv_coverage": "NBATV, MSG, CSCH",
    "provider_coverage": null,
    "seatgeek_id": "5479669",
    "last_updated": false,
    "teams": [
      "dataIslandPaths",
      "nba.g.2021120218",
      "teams"
    ],
    "play_by_play": [
      "gameplay_by_play",
      "nba.g.2021120218"
    ],
    "pitches": [
      "gamepitches",
      "nba.g.2021120218"
    ],
    "at_bat": [
      "gameat_bat",
      "nba.g.2021120218"
    ],
    "penalty_summary": [
      "gamepenalty_summary",
      "nba.g.2021120218"
    ],
    "scoring_summary": [
      "gamescoring_summary",
      "nba.g.2021120218"
    ],
    "stat_categories": [
      "game_stat_leaders"
    ],
    "stadium": [
      "gamestadium",
      "nba.g.2021120218"
    ],
    "stadium_id": [
      "gamestadium_id",
      "nba.g.2021120218"
    ],
    "stadium_image": [
      "gamestadium_image",
      "nba.g.2021120218"
    ],
    "attendance": [
      "gameattendance",
      "nba.g.2021120218"
    ],
    "lineups": [
      "gamelineups",
      "nba.g.2021120218"
    ],
    "top_performer": [
      "gametop_performer",
      "nba.g.2021120218"
    ],
    "players": [
      "dataIslandPaths",
      "nba.g.2021120218",
      "players"
    ],
    "byline": [
      "gamebyline",
      "nba.g.2021120218"
    ],
    "highlight": [
      "gamehighlight",
      "nba.g.2021120218"
    ],
    "highlights": [
      "gamehighlights",
      "nba.g.2021120218"
    ],
    "live_video": [
      "gamelive_video",
      "nba.g.2021120218"
    ],
    "odds": [
      "gameodds",
      "nba.g.2021120218"
    ],
    "current_players": [
      "gamecurrent_players",
      "nba.g.2021120218"
    ],
    "last_play": [
      "gamelast_play",
      "nba.g.2021120218"
    ],
    "series_type": [
      "gameseries_type",
      "nba.g.2021120218"
    ],
    "series_status": [
      "gameseries_status",
      "nba.g.2021120218"
    ],
    "games": [
      "dataIslandPaths",
      "nba.g.2021120218",
      "games"
    ],
    "series_games": [
      "gameseries_games",
      "nba.g.2021120218"
    ],
    "game_details": [
      "gamegame_details",
      "nba.g.2021120218"
    ],
    "section_notes": [
      "gamesection_notes",
      "nba.g.2021120218"
    ],
    "articles": [
      "dataIslandPaths",
      "nba.g.2021120218",
      "gamearticles"
    ],
    "tweets": [
      "gametweets",
      "nba.g.2021120218"
    ],
    "playoff_round": [
      "gameplayoff_round",
      "nba.g.2021120218"
    ],
    "media_stream": [
      "gamemedia_stream",
      "nba.g.2021120218"
    ],
    "playoff_series_status": [
      "gameplayoff_series_status",
      "nba.g.2021120218"
    ],
    "playoff_series_details": [
      "gameplayoff_series_details",
      "nba.g.2021120218"
    ],
    "drives": [
      "gamedrives",
      "nba.g.2021120218"
    ],
    "user_teams_game": [
      "gameuser_teams_game",
      "nba.g.2021120218"
    ],
    "page_metadata": [
      "gamepage_metadata",
      "nba.g.2021120218"
    ],
    "penalty_box": [
      "gamepenalty_box",
      "nba.g.2021120218"
    ],
    "starting_pitchers": [
      "gamestarting_pitchers",
      "nba.g.2021120218"
    ],
    "unrestricted_streams": [
      "gameunrestricted_streams",
      "nba.g.2021120218"
    ],
    "tv_details": [
      "gametv_details",
      "nba.g.2021120218"
    ],
    "away_seed": null,
    "home_seed": null
  },
  {
    "gameid": "nba.g.2021120228",
    "global_gameid": "nba.g.2374845",
    "start_time": "Fri, 03 Dec 2021 00:30:00 +0000",
    "is_time_tba": false,
    "season_phase_id": "season.phase.season",
    "game_type": "Regular Season",
    "winning_team_id": null,
    "is_rank_upset": null,
    "is_spread_upset": null,
    "outcome_type": null,
    "home_team_id": "nba.t.28",
    "away_team_id": "nba.t.15",
    "navigation_links": {
      "tickets": {
        "url": "https://seatgeek.com/toronto-raptors-tickets/?aid=14&date=2021-12-02"
      },
      "boxscore": {
        "url": "/nba/milwaukee-bucks-toronto-raptors-2021120228/"
      },
      "match_page": {
        "url": "/nba/milwaukee-bucks-toronto-raptors-2021120228/"
      },
      "league_home": {
        "url": "/nba/"
      },
      "league_scores": {
        "url": "/nba/scoreboard/"
      }
    },
    "sportacular_url": "ysportacular://v2/scores/details?gameId=nba.g.2021120228&sport=nba",
    "status_display_name": "7:30 pm ET",
    "status_description": "Pregame",
    "status_type": "status.type.pregame",
    "total_away_points": null,
    "current_period_id": null,
    "total_home_points": null,
    "total_away_shootout_points": null,
    "total_home_shootout_points": null,
    "home_team_stats": null,
    "away_team_stats": null,
    "game_period_balls": null,
    "game_period_strikes": null,
    "game_period_outs": null,
    "yards_to_endzone": null,
    "start_yardline": null,
    "distance": null,
    "down": null,
    "team_in_possession": null,
    "power_play_strength_home": null,
    "power_play_strength_away": null,
    "game_time_elapsed": null,
    "game_time_elapsed_display": null,
    "inning_status": null,
    "away_timeouts": null,
    "home_timeouts": null,
    "is_halftime": null,
    "minimum_periods": null,
    "game_periods": [],
    "baserunners": null,
    "season": "2021",
    "subleague": null,
    "subleague_display_name": null,
    "agg_score": null,
    "leg_number": null,
    "tv_coverage": "TSN, FSWI",
    "provider_coverage": null,
    "seatgeek_id": "5482445",
    "last_updated": false,
    "teams": [
      "dataIslandPaths",
      "nba.g.2021120228",
      "teams"
    ],
    "play_by_play": [
      "gameplay_by_play",
      "nba.g.2021120228"
    ],
    "pitches": [
      "gamepitches",
      "nba.g.2021120228"
    ],
    "at_bat": [
      "gameat_bat",
      "nba.g.2021120228"
    ],
    "penalty_summary": [
      "gamepenalty_summary",
      "nba.g.2021120228"
    ],
    "scoring_summary": [
      "gamescoring_summary",
      "nba.g.2021120228"
    ],
    "stat_categories": [
      "game_stat_leaders"
    ],
    "stadium": [
      "gamestadium",
      "nba.g.2021120228"
    ],
    "stadium_id": [
      "gamestadium_id",
      "nba.g.2021120228"
    ],
    "stadium_image": [
      "gamestadium_image",
      "nba.g.2021120228"
    ],
    "attendance": [
      "gameattendance",
      "nba.g.2021120228"
    ],
    "lineups": [
      "gamelineups",
      "nba.g.2021120228"
    ],
    "top_performer": [
      "gametop_performer",
      "nba.g.2021120228"
    ],
    "players": [
      "dataIslandPaths",
      "nba.g.2021120228",
      "players"
    ],
    "byline": [
      "gamebyline",
      "nba.g.2021120228"
    ],
    "highlight": [
      "gamehighlight",
      "nba.g.2021120228"
    ],
    "highlights": [
      "gamehighlights",
      "nba.g.2021120228"
    ],
    "live_video": [
      "gamelive_video",
      "nba.g.2021120228"
    ],
    "odds": [
      "gameodds",
      "nba.g.2021120228"
    ],
    "current_players": [
      "gamecurrent_players",
      "nba.g.2021120228"
    ],
    "last_play": [
      "gamelast_play",
      "nba.g.2021120228"
    ],
    "series_type": [
      "gameseries_type",
      "nba.g.2021120228"
    ],
    "series_status": [
      "gameseries_status",
      "nba.g.2021120228"
    ],
    "games": [
      "dataIslandPaths",
      "nba.g.2021120228",
      "games"
    ],
    "series_games": [
      "gameseries_games",
      "nba.g.2021120228"
    ],
    "game_details": [
      "gamegame_details",
      "nba.g.2021120228"
    ],
    "section_notes": [
      "gamesection_notes",
      "nba.g.2021120228"
    ],
    "articles": [
      "dataIslandPaths",
      "nba.g.2021120228",
      "gamearticles"
    ],
    "tweets": [
      "gametweets",
      "nba.g.2021120228"
    ],
    "playoff_round": [
      "gameplayoff_round",
      "nba.g.2021120228"
    ],
    "media_stream": [
      "gamemedia_stream",
      "nba.g.2021120228"
    ],
    "playoff_series_status": [
      "gameplayoff_series_status",
      "nba.g.2021120228"
    ],
    "playoff_series_details": [
      "gameplayoff_series_details",
      "nba.g.2021120228"
    ],
    "drives": [
      "gamedrives",
      "nba.g.2021120228"
    ],
    "user_teams_game": [
      "gameuser_teams_game",
      "nba.g.2021120228"
    ],
    "page_metadata": [
      "gamepage_metadata",
      "nba.g.2021120228"
    ],
    "penalty_box": [
      "gamepenalty_box",
      "nba.g.2021120228"
    ],
    "starting_pitchers": [
      "gamestarting_pitchers",
      "nba.g.2021120228"
    ],
    "unrestricted_streams": [
      "gameunrestricted_streams",
      "nba.g.2021120228"
    ],
    "tv_details": [
      "gametv_details",
      "nba.g.2021120228"
    ],
    "away_seed": null,
    "home_seed": null
  },
  {
    "gameid": "nba.g.2021120229",
    "global_gameid": "nba.g.2374485",
    "start_time": "Fri, 03 Dec 2021 01:00:00 +0000",
    "is_time_tba": false,
    "season_phase_id": "season.phase.season",
    "game_type": "Regular Season",
    "winning_team_id": null,
    "is_rank_upset": null,
    "is_spread_upset": null,
    "outcome_type": null,
    "home_team_id": "nba.t.29",
    "away_team_id": "nba.t.25",
    "navigation_links": {
      "tickets": {
        "url": "https://seatgeek.com/memphis-grizzlies-tickets/?aid=14&date=2021-12-02"
      },
      "boxscore": {
        "url": "/nba/oklahoma-city-thunder-memphis-grizzlies-2021120229/"
      },
      "match_page": {
        "url": "/nba/oklahoma-city-thunder-memphis-grizzlies-2021120229/"
      },
      "league_home": {
        "url": "/nba/"
      },
      "league_scores": {
        "url": "/nba/scoreboard/"
      }
    },
    "sportacular_url": "ysportacular://v2/scores/details?gameId=nba.g.2021120229&sport=nba",
    "status_display_name": "8:00 pm ET",
    "status_description": "Pregame",
    "status_type": "status.type.pregame",
    "total_away_points": null,
    "current_period_id": null,
    "total_home_points": null,
    "total_away_shootout_points": null,
    "total_home_shootout_points": null,
    "home_team_stats": null,
    "away_team_stats": null,
    "game_period_balls": null,
    "game_period_strikes": null,
    "game_period_outs": null,
    "yards_to_endzone": null,
    "start_yardline": null,
    "distance": null,
    "down": null,
    "team_in_possession": null,
    "power_play_strength_home": null,
    "power_play_strength_away": null,
    "game_time_elapsed": null,
    "game_time_elapsed_display": null,
    "inning_status": null,
    "away_timeouts": null,
    "home_timeouts": null,
    "is_halftime": null,
    "minimum_periods": null,
    "game_periods": [],
    "baserunners": null,
    "season": "2021",
    "subleague": null,
    "subleague_display_name": null,
    "agg_score": null,
    "leg_number": null,
    "tv_coverage": "BSOK, BSTN",
    "provider_coverage": null,
    "seatgeek_id": "5480801",
    "last_updated": false,
    "teams": [
      "dataIslandPaths",
      "nba.g.2021120229",
      "teams"
    ],
    "play_by_play": [
      "gameplay_by_play",
      "nba.g.2021120229"
    ],
    "pitches": [
      "gamepitches",
      "nba.g.2021120229"
    ],
    "at_bat": [
      "gameat_bat",
      "nba.g.2021120229"
    ],
    "penalty_summary": [
      "gamepenalty_summary",
      "nba.g.2021120229"
    ],
    "scoring_summary": [
      "gamescoring_summary",
      "nba.g.2021120229"
    ],
    "stat_categories": [
      "game_stat_leaders"
    ],
    "stadium": [
      "gamestadium",
      "nba.g.2021120229"
    ],
    "stadium_id": [
      "gamestadium_id",
      "nba.g.2021120229"
    ],
    "stadium_image": [
      "gamestadium_image",
      "nba.g.2021120229"
    ],
    "attendance": [
      "gameattendance",
      "nba.g.2021120229"
    ],
    "lineups": [
      "gamelineups",
      "nba.g.2021120229"
    ],
    "top_performer": [
      "gametop_performer",
      "nba.g.2021120229"
    ],
    "players": [
      "dataIslandPaths",
      "nba.g.2021120229",
      "players"
    ],
    "byline": [
      "gamebyline",
      "nba.g.2021120229"
    ],
    "highlight": [
      "gamehighlight",
      "nba.g.2021120229"
    ],
    "highlights": [
      "gamehighlights",
      "nba.g.2021120229"
    ],
    "live_video": [
      "gamelive_video",
      "nba.g.2021120229"
    ],
    "odds": [
      "gameodds",
      "nba.g.2021120229"
    ],
    "current_players": [
      "gamecurrent_players",
      "nba.g.2021120229"
    ],
    "last_play": [
      "gamelast_play",
      "nba.g.2021120229"
    ],
    "series_type": [
      "gameseries_type",
      "nba.g.2021120229"
    ],
    "series_status": [
      "gameseries_status",
      "nba.g.2021120229"
    ],
    "games": [
      "dataIslandPaths",
      "nba.g.2021120229",
      "games"
    ],
    "series_games": [
      "gameseries_games",
      "nba.g.2021120229"
    ],
    "game_details": [
      "gamegame_details",
      "nba.g.2021120229"
    ],
    "section_notes": [
      "gamesection_notes",
      "nba.g.2021120229"
    ],
    "articles": [
      "dataIslandPaths",
      "nba.g.2021120229",
      "gamearticles"
    ],
    "tweets": [
      "gametweets",
      "nba.g.2021120229"
    ],
    "playoff_round": [
      "gameplayoff_round",
      "nba.g.2021120229"
    ],
    "media_stream": [
      "gamemedia_stream",
      "nba.g.2021120229"
    ],
    "playoff_series_status": [
      "gameplayoff_series_status",
      "nba.g.2021120229"
    ],
    "playoff_series_details": [
      "gameplayoff_series_details",
      "nba.g.2021120229"
    ],
    "drives": [
      "gamedrives",
      "nba.g.2021120229"
    ],
    "user_teams_game": [
      "gameuser_teams_game",
      "nba.g.2021120229"
    ],
    "page_metadata": [
      "gamepage_metadata",
      "nba.g.2021120229"
    ],
    "penalty_box": [
      "gamepenalty_box",
      "nba.g.2021120229"
    ],
    "starting_pitchers": [
      "gamestarting_pitchers",
      "nba.g.2021120229"
    ],
    "unrestricted_streams": [
      "gameunrestricted_streams",
      "nba.g.2021120229"
    ],
    "tv_details": [
      "gametv_details",
      "nba.g.2021120229"
    ],
    "away_seed": null,
    "home_seed": null
  },
  {
    "gameid": "nba.g.2021120221",
    "global_gameid": "nba.g.2374914",
    "start_time": "Fri, 03 Dec 2021 02:00:00 +0000",
    "is_time_tba": false,
    "season_phase_id": "season.phase.season",
    "game_type": "Regular Season",
    "winning_team_id": null,
    "is_rank_upset": null,
    "is_spread_upset": null,
    "outcome_type": null,
    "home_team_id": "nba.t.21",
    "away_team_id": "nba.t.8",
    "navigation_links": {
      "tickets": {
        "url": "https://seatgeek.com/phoenix-suns-tickets/?aid=14&date=2021-12-02"
      },
      "boxscore": {
        "url": "/nba/detroit-pistons-phoenix-suns-2021120221/"
      },
      "match_page": {
        "url": "/nba/detroit-pistons-phoenix-suns-2021120221/"
      },
      "league_home": {
        "url": "/nba/"
      },
      "league_scores": {
        "url": "/nba/scoreboard/"
      }
    },
    "sportacular_url": "ysportacular://v2/scores/details?gameId=nba.g.2021120221&sport=nba",
    "status_display_name": "9:00 pm ET",
    "status_description": "Pregame",
    "status_type": "status.type.pregame",
    "total_away_points": null,
    "current_period_id": null,
    "total_home_points": null,
    "total_away_shootout_points": null,
    "total_home_shootout_points": null,
    "home_team_stats": null,
    "away_team_stats": null,
    "game_period_balls": null,
    "game_period_strikes": null,
    "game_period_outs": null,
    "yards_to_endzone": null,
    "start_yardline": null,
    "distance": null,
    "down": null,
    "team_in_possession": null,
    "power_play_strength_home": null,
    "power_play_strength_away": null,
    "game_time_elapsed": null,
    "game_time_elapsed_display": null,
    "inning_status": null,
    "away_timeouts": null,
    "home_timeouts": null,
    "is_halftime": null,
    "minimum_periods": null,
    "game_periods": [],
    "baserunners": null,
    "season": "2021",
    "subleague": null,
    "subleague_display_name": null,
    "agg_score": null,
    "leg_number": null,
    "tv_coverage": "BSD, BSAZ",
    "provider_coverage": null,
    "seatgeek_id": "5480151",
    "last_updated": false,
    "teams": [
      "dataIslandPaths",
      "nba.g.2021120221",
      "teams"
    ],
    "play_by_play": [
      "gameplay_by_play",
      "nba.g.2021120221"
    ],
    "pitches": [
      "gamepitches",
      "nba.g.2021120221"
    ],
    "at_bat": [
      "gameat_bat",
      "nba.g.2021120221"
    ],
    "penalty_summary": [
      "gamepenalty_summary",
      "nba.g.2021120221"
    ],
    "scoring_summary": [
      "gamescoring_summary",
      "nba.g.2021120221"
    ],
    "stat_categories": [
      "game_stat_leaders"
    ],
    "stadium": [
      "gamestadium",
      "nba.g.2021120221"
    ],
    "stadium_id": [
      "gamestadium_id",
      "nba.g.2021120221"
    ],
    "stadium_image": [
      "gamestadium_image",
      "nba.g.2021120221"
    ],
    "attendance": [
      "gameattendance",
      "nba.g.2021120221"
    ],
    "lineups": [
      "gamelineups",
      "nba.g.2021120221"
    ],
    "top_performer": [
      "gametop_performer",
      "nba.g.2021120221"
    ],
    "players": [
      "dataIslandPaths",
      "nba.g.2021120221",
      "players"
    ],
    "byline": [
      "gamebyline",
      "nba.g.2021120221"
    ],
    "highlight": [
      "gamehighlight",
      "nba.g.2021120221"
    ],
    "highlights": [
      "gamehighlights",
      "nba.g.2021120221"
    ],
    "live_video": [
      "gamelive_video",
      "nba.g.2021120221"
    ],
    "odds": [
      "gameodds",
      "nba.g.2021120221"
    ],
    "current_players": [
      "gamecurrent_players",
      "nba.g.2021120221"
    ],
    "last_play": [
      "gamelast_play",
      "nba.g.2021120221"
    ],
    "series_type": [
      "gameseries_type",
      "nba.g.2021120221"
    ],
    "series_status": [
      "gameseries_status",
      "nba.g.2021120221"
    ],
    "games": [
      "dataIslandPaths",
      "nba.g.2021120221",
      "games"
    ],
    "series_games": [
      "gameseries_games",
      "nba.g.2021120221"
    ],
    "game_details": [
      "gamegame_details",
      "nba.g.2021120221"
    ],
    "section_notes": [
      "gamesection_notes",
      "nba.g.2021120221"
    ],
    "articles": [
      "dataIslandPaths",
      "nba.g.2021120221",
      "gamearticles"
    ],
    "tweets": [
      "gametweets",
      "nba.g.2021120221"
    ],
    "playoff_round": [
      "gameplayoff_round",
      "nba.g.2021120221"
    ],
    "media_stream": [
      "gamemedia_stream",
      "nba.g.2021120221"
    ],
    "playoff_series_status": [
      "gameplayoff_series_status",
      "nba.g.2021120221"
    ],
    "playoff_series_details": [
      "gameplayoff_series_details",
      "nba.g.2021120221"
    ],
    "drives": [
      "gamedrives",
      "nba.g.2021120221"
    ],
    "user_teams_game": [
      "gameuser_teams_game",
      "nba.g.2021120221"
    ],
    "page_metadata": [
      "gamepage_metadata",
      "nba.g.2021120221"
    ],
    "penalty_box": [
      "gamepenalty_box",
      "nba.g.2021120221"
    ],
    "starting_pitchers": [
      "gamestarting_pitchers",
      "nba.g.2021120221"
    ],
    "unrestricted_streams": [
      "gameunrestricted_streams",
      "nba.g.2021120221"
    ],
    "tv_details": [
      "gametv_details",
      "nba.g.2021120221"
    ],
    "away_seed": null,
    "home_seed": null
  },
  {
    "gameid": "nba.g.2021120222",
    "global_gameid": "nba.g.2374982",
    "start_time": "Fri, 03 Dec 2021 03:00:00 +0000",
    "is_time_tba": false,
    "season_phase_id": "season.phase.season",
    "game_type": "Regular Season",
    "winning_team_id": null,
    "is_rank_upset": null,
    "is_spread_upset": null,
    "outcome_type": null,
    "home_team_id": "nba.t.22",
    "away_team_id": "nba.t.24",
    "navigation_links": {
      "tickets": {
        "url": "https://seatgeek.com/portland-trail-blazers-tickets/?aid=14&date=2021-12-02"
      },
      "boxscore": {
        "url": "/nba/san-antonio-spurs-portland-trail-blazers-2021120222/"
      },
      "match_page": {
        "url": "/nba/san-antonio-spurs-portland-trail-blazers-2021120222/"
      },
      "league_home": {
        "url": "/nba/"
      },
      "league_scores": {
        "url": "/nba/scoreboard/"
      }
    },
    "sportacular_url": "ysportacular://v2/scores/details?gameId=nba.g.2021120222&sport=nba",
    "status_display_name": "10:00 pm ET",
    "status_description": "Pregame",
    "status_type": "status.type.pregame",
    "total_away_points": null,
    "current_period_id": null,
    "total_home_points": null,
    "total_away_shootout_points": null,
    "total_home_shootout_points": null,
    "home_team_stats": null,
    "away_team_stats": null,
    "game_period_balls": null,
    "game_period_strikes": null,
    "game_period_outs": null,
    "yards_to_endzone": null,
    "start_yardline": null,
    "distance": null,
    "down": null,
    "team_in_possession": null,
    "power_play_strength_home": null,
    "power_play_strength_away": null,
    "game_time_elapsed": null,
    "game_time_elapsed_display": null,
    "inning_status": null,
    "away_timeouts": null,
    "home_timeouts": null,
    "is_halftime": null,
    "minimum_periods": null,
    "game_periods": [],
    "baserunners": null,
    "season": "2021",
    "subleague": null,
    "subleague_display_name": null,
    "agg_score": null,
    "leg_number": null,
    "tv_coverage": "NBATV, BSSW",
    "provider_coverage": null,
    "seatgeek_id": "5480635",
    "last_updated": false,
    "teams": [
      "dataIslandPaths",
      "nba.g.2021120222",
      "teams"
    ],
    "play_by_play": [
      "gameplay_by_play",
      "nba.g.2021120222"
    ],
    "pitches": [
      "gamepitches",
      "nba.g.2021120222"
    ],
    "at_bat": [
      "gameat_bat",
      "nba.g.2021120222"
    ],
    "penalty_summary": [
      "gamepenalty_summary",
      "nba.g.2021120222"
    ],
    "scoring_summary": [
      "gamescoring_summary",
      "nba.g.2021120222"
    ],
    "stat_categories": [
      "game_stat_leaders"
    ],
    "stadium": [
      "gamestadium",
      "nba.g.2021120222"
    ],
    "stadium_id": [
      "gamestadium_id",
      "nba.g.2021120222"
    ],
    "stadium_image": [
      "gamestadium_image",
      "nba.g.2021120222"
    ],
    "attendance": [
      "gameattendance",
      "nba.g.2021120222"
    ],
    "lineups": [
      "gamelineups",
      "nba.g.2021120222"
    ],
    "top_performer": [
      "gametop_performer",
      "nba.g.2021120222"
    ],
    "players": [
      "dataIslandPaths",
      "nba.g.2021120222",
      "players"
    ],
    "byline": [
      "gamebyline",
      "nba.g.2021120222"
    ],
    "highlight": [
      "gamehighlight",
      "nba.g.2021120222"
    ],
    "highlights": [
      "gamehighlights",
      "nba.g.2021120222"
    ],
    "live_video": [
      "gamelive_video",
      "nba.g.2021120222"
    ],
    "odds": [
      "gameodds",
      "nba.g.2021120222"
    ],
    "current_players": [
      "gamecurrent_players",
      "nba.g.2021120222"
    ],
    "last_play": [
      "gamelast_play",
      "nba.g.2021120222"
    ],
    "series_type": [
      "gameseries_type",
      "nba.g.2021120222"
    ],
    "series_status": [
      "gameseries_status",
      "nba.g.2021120222"
    ],
    "games": [
      "dataIslandPaths",
      "nba.g.2021120222",
      "games"
    ],
    "series_games": [
      "gameseries_games",
      "nba.g.2021120222"
    ],
    "game_details": [
      "gamegame_details",
      "nba.g.2021120222"
    ],
    "section_notes": [
      "gamesection_notes",
      "nba.g.2021120222"
    ],
    "articles": [
      "dataIslandPaths",
      "nba.g.2021120222",
      "gamearticles"
    ],
    "tweets": [
      "gametweets",
      "nba.g.2021120222"
    ],
    "playoff_round": [
      "gameplayoff_round",
      "nba.g.2021120222"
    ],
    "media_stream": [
      "gamemedia_stream",
      "nba.g.2021120222"
    ],
    "playoff_series_status": [
      "gameplayoff_series_status",
      "nba.g.2021120222"
    ],
    "playoff_series_details": [
      "gameplayoff_series_details",
      "nba.g.2021120222"
    ],
    "drives": [
      "gamedrives",
      "nba.g.2021120222"
    ],
    "user_teams_game": [
      "gameuser_teams_game",
      "nba.g.2021120222"
    ],
    "page_metadata": [
      "gamepage_metadata",
      "nba.g.2021120222"
    ],
    "penalty_box": [
      "gamepenalty_box",
      "nba.g.2021120222"
    ],
    "starting_pitchers": [
      "gamestarting_pitchers",
      "nba.g.2021120222"
    ],
    "unrestricted_streams": [
      "gameunrestricted_streams",
      "nba.g.2021120222"
    ],
    "tv_details": [
      "gametv_details",
      "nba.g.2021120222"
    ],
    "away_seed": null,
    "home_seed": null
  }
]